intermittent_levy/__init__.py
intermittent_levy/classification.py
intermittent_levy/moments.py
intermittent_levy/optimization.py
intermittent_levy/processes.py
intermittent_levy/utils.py
intermittent_levy/tests/__init__.py
intermittent_levy/tests/test_classification.py
intermittent_levy/tests/test_moments.py
intermittent_levy/tests/test_optimization.py
intermittent_levy/tests/test_processes.py
intermittent_levy-0.4.dist-info/LICENSE
intermittent_levy-0.4.dist-info/METADATA
intermittent_levy-0.4.dist-info/WHEEL
intermittent_levy-0.4.dist-info/top_level.txt
intermittent_levy-0.4.dist-info/RECORD
